ai_code_validator/__init__.py
ai_code_validator/analyzer.py
ai_code_validator/cli.py
ai_code_validator/dependency_checker.py
ai_code_validator/reporter.py
ai_code_validator/scorer.py
ai_code_validator/security_scanner.py
ai_code_validator-0.1.0.dist-info/licenses/LICENSE
ai_code_validator-0.1.0.dist-info/METADATA
ai_code_validator-0.1.0.dist-info/WHEEL
ai_code_validator-0.1.0.dist-info/entry_points.txt
ai_code_validator-0.1.0.dist-info/top_level.txt
ai_code_validator-0.1.0.dist-info/RECORD
